suitetecsa_core/__init__.py
suitetecsa_core/core/__init__.py
suitetecsa_core/core/exceptions.py
suitetecsa_core/domain/__init__.py
suitetecsa_core/domain/model/__init__.py
suitetecsa_core/domain/model/connection.py
suitetecsa_core/domain/model/connections_summary.py
suitetecsa_core/domain/model/nauta_user.py
suitetecsa_core/domain/model/quote_paid.py
suitetecsa_core/domain/model/quotes_paid_summary.py
suitetecsa_core/domain/model/recharge.py
suitetecsa_core/domain/model/recharges_summary.py
suitetecsa_core/domain/model/transfer.py
suitetecsa_core/domain/model/transfers_summary.py
suitetecsa_core/domain/service/nauta_client.py
suitetecsa_core/repository/scrapper_provider.py
suitetecsa_core/repository/session_provider.py
suitetecsa_core/utils/__init__.py
suitetecsa_core/utils/nauta.py
suitetecsa_core/utils/parser.py
suitetecsa_core-1.1.0.dist-info/LICENSE
suitetecsa_core-1.1.0.dist-info/METADATA
suitetecsa_core-1.1.0.dist-info/WHEEL
suitetecsa_core-1.1.0.dist-info/top_level.txt
suitetecsa_core-1.1.0.dist-info/RECORD
