Metadata-Version: 2.1
Name: suitetecsa-core
Version: 1.1.0
Summary: Una API que interactúa con los servicios web de ETECSA. 
Home-page: https://github.com/SuitETECSA/suitetecsa-sdk-python
Author: lesclaz
Author-email: lesclaz95@gmail.com
License: MIT
Keywords: ETECSA nauta tools
Platform: Unix
Classifier: Topic :: Internet
Classifier: License :: OSI Approved :: MIT License
Classifier: Programming Language :: Python :: 3
Classifier: Development Status :: 4 - Beta
Classifier: Operating System :: Unix
License-File: LICENSE
Requires-Dist: requests
Requires-Dist: beautifulsoup4
Requires-Dist: setuptools
Requires-Dist: html5lib
Requires-Dist: netifaces
